fplib.py
fplib-0.1.1.dist-info/DESCRIPTION.rst
fplib-0.1.1.dist-info/METADATA
fplib-0.1.1.dist-info/RECORD
fplib-0.1.1.dist-info/WHEEL
fplib-0.1.1.dist-info/metadata.json
fplib-0.1.1.dist-info/top_level.txt
