Metadata-Version: 2.0
Name: fplib
Version: 0.1.1
Summary: A functional programming library for python.
Home-page: https://github.com/hruskamiro/fplib
Author: Miroslav Hruska
Author-email: hruska.miro@gmail.com
License: MIT
Keywords: functional programming
Platform: UNKNOWN
